sql_to_pandas/__init__.py
sql_to_pandas/sql_to_pandas.py
sql_to_pandas/helpers/__init__.py
sql_to_pandas/helpers/helpers.py
sql_to_pandas/helpers/keywords.py
sql_to_pandas/select/__init__.py
sql_to_pandas/select/select.py
sql_to_pandas/where/__init__.py
sql_to_pandas/where/where.py
sqltopandas-0.2.dist-info/LICENSE
sqltopandas-0.2.dist-info/METADATA
sqltopandas-0.2.dist-info/WHEEL
sqltopandas-0.2.dist-info/top_level.txt
sqltopandas-0.2.dist-info/RECORD
