Metadata-Version: 2.1
Name: sqltopandas
Version: 0.2
Summary: Use SQL expressions to query Pandas DataFrames
Home-page: https://github.com/jlehrer1/sql-to-pandas
Author: Julian Lehrer
Author-email: julianmlehrer@gmail.com
License: MIT
Keywords: SQL,PYTHON,DATA SCIENCE,PANDAS,DATAFRAME
Platform: UNKNOWN
Classifier: Development Status :: 3 - Alpha
Classifier: Intended Audience :: Developers
Classifier: Topic :: Software Development :: Build Tools
Classifier: License :: OSI Approved :: MIT License
Classifier: Programming Language :: Python :: 3.8
Requires-Dist: numpy
Requires-Dist: pandas
Requires-Dist: sqlparse
Requires-Dist: pytest
